LICENSE.md
MANIFEST.in
README.md
setup.py
chainforge/__init__.py
chainforge/app.py
chainforge/flask_app.py
chainforge.egg-info/PKG-INFO
chainforge.egg-info/SOURCES.txt
chainforge.egg-info/dependency_links.txt
chainforge.egg-info/entry_points.txt
chainforge.egg-info/requires.txt
chainforge.egg-info/top_level.txt
chainforge/examples/.DS_Store
chainforge/examples/animal-images.cforge
chainforge/examples/audit-bias.cforge
chainforge/examples/basic-comparison.cforge
chainforge/examples/basic-function-calls.cforge
chainforge/examples/basic-math.cforge
chainforge/examples/book-beginnings.cforge
chainforge/examples/chaining-prompts.cforge
chainforge/examples/chat-sycophancy.cforge
chainforge/examples/compare-prompts.cforge
chainforge/examples/comparing-formats.cforge
chainforge/examples/comparing-system-msg.cforge
chainforge/examples/custom_provider_cohere.py
chainforge/examples/mosquito-knowledge.cforge
chainforge/examples/prompt-injection-test.cforge
chainforge/examples/python-coding-eval.cforge
chainforge/examples/red-team-stereotypes.cforge
chainforge/examples/structured-outputs.cforge
chainforge/examples/tweet-multi-eval.cforge
chainforge/examples/oaievals/2d_movement.cforge
chainforge/examples/oaievals/adultery_state_laws.cforge
chainforge/examples/oaievals/aime_evaluation.cforge
chainforge/examples/oaievals/algebra-word-problems.cforge
chainforge/examples/oaievals/ambiguous-sentences.cforge
chainforge/examples/oaievals/bitwise.cforge
chainforge/examples/oaievals/born-first.cforge
chainforge/examples/oaievals/brazilian_laws.cforge
chainforge/examples/oaievals/chess-piece-count.cforge
chainforge/examples/oaievals/chess.cforge
chainforge/examples/oaievals/compare-countries-area.cforge
chainforge/examples/oaievals/counterfactual-reasoning.cforge
chainforge/examples/oaievals/countries.cforge
chainforge/examples/oaievals/cricket_situations.cforge
chainforge/examples/oaievals/day-of-week-from-date.cforge
chainforge/examples/oaievals/directions.cforge
chainforge/examples/oaievals/french-part-of-speech.cforge
chainforge/examples/oaievals/guess-the-singer.cforge
chainforge/examples/oaievals/hebrew-same-noun-gender.cforge
chainforge/examples/oaievals/hindi_words.cforge
