Metadata-Version: 2.4
Name: chainforge
Version: 0.3.6.4
Summary: A Visual Programming Environment for Prompt Engineering
Home-page: https://github.com/ianarawjo/ChainForge/
Author: Ian Arawjo
License: MIT
Keywords: prompt engineering LLM response evaluation
Classifier: Development Status :: 3 - Alpha
Classifier: Intended Audience :: Developers
Classifier: License :: OSI Approved :: MIT License
Classifier: Programming Language :: Python :: 3
Classifier: Programming Language :: Python :: 3.10
Classifier: Programming Language :: Python :: 3.11
Classifier: Programming Language :: Python :: 3.12
Requires-Python: >=3.10
License-File: LICENSE.md
Requires-Dist: flask>=2.2.3
Requires-Dist: flask[async]
Requires-Dist: flask_cors
Requires-Dist: requests
Requires-Dist: platformdirs
Requires-Dist: urllib3==1.26.6
Requires-Dist: openai
Requires-Dist: cryptography
Requires-Dist: mistune>=2.0
Requires-Dist: markitdown[docx,pdf,pptx,xls,xlsx]
Dynamic: author
Dynamic: classifier
Dynamic: description
Dynamic: description-content-type
Dynamic: home-page
Dynamic: keywords
Dynamic: license
Dynamic: license-file
Dynamic: requires-dist
Dynamic: requires-python
Dynamic: summary
